fast_auth/__init__.py
fast_auth/config.py
fast_auth/main.py
fast_auth/auth/__init__.py
fast_auth/auth/db.py
fast_auth/auth/models.py
fast_auth/auth/routes.py
fast_auth/auth/utils.py
fast_auth_routes-0.1.0.dist-info/METADATA
fast_auth_routes-0.1.0.dist-info/WHEEL
fast_auth_routes-0.1.0.dist-info/top_level.txt
fast_auth_routes-0.1.0.dist-info/RECORD
