Metadata-Version: 2.1
Name: fast-auth-routes
Version: 0.1.0
Summary: A simple FastAPI application with authentication and user management
Home-page: https://github.com/seunome/myapp
Author: Ewerton Azevedo
Author-email: ewertonzvd@gmail.com
Classifier: Programming Language :: Python :: 3
Classifier: License :: OSI Approved :: MIT License
Classifier: Operating System :: OS Independent
Requires-Python: >=3.11
Requires-Dist: fastapi
Requires-Dist: uvicorn
Requires-Dist: pydantic
Requires-Dist: passlib[bcrypt]
Requires-Dist: python-jose[cryptography]
Requires-Dist: motor
